neurospeed/__init__.py
neurospeed/constants.py
neurospeed/api_http_handlers/__init__.py
neurospeed/api_http_handlers/customer_account_manager.py
neurospeed/api_http_handlers/exporter_http_handler.py
neurospeed/api_http_handlers/gateway_http_handler.py
neurospeed/api_http_handlers/insight_http_handler.py
neurospeed/api_http_handlers/recorder_http_handler.py
neurospeed/api_http_handlers/ssr_http_handler.py
neurospeed/api_socket_handlers/__init__.py
neurospeed/api_socket_handlers/customer_room_handler.py
neurospeed/api_socket_handlers/downlink_room_as_customer_handler.py
neurospeed/api_socket_handlers/downlink_room_as_user_handler.py
neurospeed/api_socket_handlers/user_room_as_customer_handler.py
neurospeed/api_socket_handlers/user_room_as_user_handler.py
neurospeed/auth/__init__.py
neurospeed/auth/auth_as_customer_handler.py
neurospeed/auth/auth_as_user_handler.py
neurospeed/config/api_config.json
neurospeed/config/customer_config.json
neurospeed/config/hia_config1.json
neurospeed/config/hia_config2.json
neurospeed/hia_user_data/__init__.py
neurospeed/hia_user_data/neurobrave_sensor_interface.py
neurospeed/macros/__init__.py
neurospeed/macros/macros.py
neurospeed/utils/__init__.py
neurospeed/utils/api_config_service.py
neurospeed/utils/helper_service.py
neurospeed/utils/http_service.py
neurospeed-2.3.5.dist-info/LICENSE.txt
neurospeed-2.3.5.dist-info/METADATA
neurospeed-2.3.5.dist-info/WHEEL
neurospeed-2.3.5.dist-info/top_level.txt
neurospeed-2.3.5.dist-info/RECORD
