Metadata-Version: 2.1
Name: neurospeed
Version: 2.3.5
Summary: NeuroSpeed Python API
Home-page: https://bitbucket.org/neurobrave/neurospeed_python_api
Author: NeuroBrave
License: LICENSE.txt
Classifier: Programming Language :: Python :: 3
Classifier: License :: OSI Approved :: MIT License
Classifier: Operating System :: OS Independent
License-File: LICENSE.txt
Requires-Dist: python-socketio[client]==5.3.0
